konciliation/__init__.py
konciliation/__main__.py
konciliation/__version__.py
konciliation/main.py
konciliation/main_widget.py
konciliation/sup.py
konciliation_GDV_target_task-0.3.1.dist-info/METADATA
konciliation_GDV_target_task-0.3.1.dist-info/WHEEL
konciliation_GDV_target_task-0.3.1.dist-info/entry_points.txt
konciliation_GDV_target_task-0.3.1.dist-info/top_level.txt
konciliation_GDV_target_task-0.3.1.dist-info/RECORD
